ccl_scratch_scrape/__init__.py
ccl_scratch_scrape/scrape.py
ccl_scratch_scrape-0.0.3.dist-info/LICENSE
ccl_scratch_scrape-0.0.3.dist-info/METADATA
ccl_scratch_scrape-0.0.3.dist-info/WHEEL
ccl_scratch_scrape-0.0.3.dist-info/top_level.txt
ccl_scratch_scrape-0.0.3.dist-info/RECORD
