Metadata-Version: 2.1
Name: ccl-scratch-scrape
Version: 0.0.3
Summary: Tools by which to scrape Scratch JSON files.
Home-page: https://github.com/GSE-CCL/scratch-studio-scrape
Author: Creative Computing Lab
Author-email: jarchibald@college.harvard.edu
License: UNKNOWN
Platform: UNKNOWN
Classifier: Programming Language :: Python :: 3
Classifier: License :: OSI Approved :: MIT License
Classifier: Operating System :: OS Independent
Requires-Python: >=3.7
Requires-Dist: requests
